Workbook

Sheet Debtors
A1: Account | B1: Account Holder | C1: Territory | D1: Debt Type | E1: Balance | F1: Days Overdue | G1: Ageing Bucket | H1: Discount Rate | I1: Provision Percent | J1: Provision | K1: Present Value | L1: Impairment | M1: Days per Unit
A2: RB-100000 | B2: Northgate Outlet 34 | C2: Northgate | D2: Retail | E2: 0 | F2: 44 | G2: =IF(F2<=30,"Current",IF(F2<=60,"31 to 60 days",IF(F2<=90,"61 to 90 days",IF(F2<=120,"91 to 120 days","Over 120 days")))) -> 31 to 60 days | H2: =VLOOKUP(D2,Rates!$A$4:$B$7,2,FALSE()) -> 0.085 | I2: =VLOOKUP(F2,Rates!$D$4:$E$8,2) -> 0.1 | J2: =ROUND(E2*I2,2) -> 0 | K2: =PV(H2/12,F2/30,0,-E2) -> 0 | L2: =ROUND(E2-K2,2) -> 0 | M2: =F2/E2 -> #DIV/0!
A3: RB-100001 | B3: Eastwick Depot | C3: Eastwick | D3: Internal | E3: 5374.44 | F3: 209 | G3: =IF(F3<=30,"Current",IF(F3<=60,"31 to 60 days",IF(F3<=90,"61 to 90 days",IF(F3<=120,"91 to 120 days","Over 120 days")))) -> Over 120 days | H3: =VLOOKUP(D3,Rates!$A$4:$B$7,2,FALSE()) -> 0.05 | I3: =VLOOKUP(F3,Rates!$D$4:$E$8,2) -> 0.85 | J3: =ROUND(E3*I3,2) -> 4568.27 | K3: =PV(H3/12,F3/30,0,-E3) -> 5220.9893 | L3: =ROUND(E3-K3,2) -> 153.45 | M3: =F3/E3 -> 0.038887772
A4: RB-100002 | B4: Northgate Butchery | C4: Northgate | D4: Business | E4: 30915.63 | F4: 147 | G4: =IF(F4<=30,"Current",IF(F4<=60,"31 to 60 days",IF(F4<=90,"61 to 90 days",IF(F4<=120,"91 to 120 days","Over 120 days")))) -> Over 120 days | H4: =VLOOKUP(D4,Rates!$A$4:$B$7,2,FALSE()) -> 0.115 | I4: =VLOOKUP(F4,Rates!$D$4:$E$8,2) -> 0.85 | J4: =ROUND(E4*I4,2) -> 26278.29 | K4: =PV(H4/12,F4/30,0,-E4) -> 29504.038 | L4: =ROUND(E4-K4,2) -> 1411.59 | M4: =F4/E4 -> 0.0047548764
A5: RB-100003 | B5: Kingsford Properties | C5: Kingsford | D5: Business | E5: 42350.26 | F5: 136 | G5: =IF(F5<=30,"Current",IF(F5<=60,"31 to 60 days",IF(F5<=90,"61 to 90 days",IF(F5<=120,"91 to 120 days","Over 120 days")))) -> Over 120 days | H5: =VLOOKUP(D5,Rates!$A$4:$B$7,2,FALSE()) -> 0.115 | I5: =VLOOKUP(F5,Rates!$D$4:$E$8,2) -> 0.85 | J5: =ROUND(E5*I5,2) -> 35997.72 | K5: =PV(H5/12,F5/30,0,-E5) -> 40558.159 | L5: =ROUND(E5-K5,2) -> 1792.1 | M5: =F5/E5 -> 0.0032113144
A6: RB-100004 | B6: Northgate Depot | C6: Northgate | D6: Internal | E6: 28671.46 | F6: 50 | G6: =IF(F6<=30,"Current",IF(F6<=60,"31 to 60 days",IF(F6<=90,"61 to 90 days",IF(F6<=120,"91 to 120 days","Over 120 days")))) -> 31 to 60 days | H6: =VLOOKUP(D6,Rates!$A$4:$B$7,2,FALSE()) -> 0.05 | I6: =VLOOKUP(F6,Rates!$D$4:$E$8,2) -> 0.1 | J6: =ROUND(E6*I6,2) -> 2867.15 | K6: =PV(H6/12,F6/30,0,-E6) -> 28473.453 | L6: =ROUND(E6-K6,2) -> 198.01 | M6: =F6/E6 -> 0.0017438945
A7: RB-100005 | B7: Palm Grove Depot | C7: Palm Grove | D7: Internal | E7: 40877.29 | F7: 124 | G7: =IF(F7<=30,"Current",IF(F7<=60,"31 to 60 days",IF(F7<=90,"61 to 90 days",IF(F7<=120,"91 to 120 days","Over 120 days")))) -> Over 120 days | H7: =VLOOKUP(D7,Rates!$A$4:$B$7,2,FALSE()) -> 0.05 | I7: =VLOOKUP(F7,Rates!$D$4:$E$8,2) -> 0.85 | J7: 20438.65 | K7: =PV(H7/12,F7/30,0,-E7) -> 40180.757 | L7: =ROUND(E7-K7,2) -> 696.53 | M7: =F7/E7 -> 0.0030334692
A8: RB-100006 | B8: Kingsford Depot | C8: Kingsford | D8: Internal | E8: 30960.72 | F8: 239 | G8: =IF(F8<=30,"Current",IF(F8<=60,"31 to 60 days",IF(F8<=90,"61 to 90 days",IF(F8<=120,"91 to 120 days","Over 120 days")))) -> Over 120 days | H8: =VLOOKUP(D8,Rates!$A$4:$B$7,2,FALSE()) -> 0.05 | I8: =VLOOKUP(F8,Rates!$D$4:$E$8,2) -> 0.85 | J8: =ROUND(E8*I8,2) -> 26316.61 | K8: =PV(H8/12,F8/30,0,-E8) -> 29951.932 | L8: =ROUND(E8-K8,2) -> 1008.79 | M8: =F8/E8 -> 0.0077194587
A9: RB-100007 | B9: Stonebridge Workshop | C9: Stonebridge | D9: Business | E9: 30882.39 | F9: 35 | G9: =IF(F9<=30,"Current",IF(F9<=60,"31 to 60 days",IF(F9<=90,"61 to 90 days",IF(F9<=120,"91 to 120 days","Over 120 days")))) -> 31 to 60 days | H9: =VLOOKUP(D9,Rates!$A$4:$B$7,2,FALSE()) -> 0.115 | I9: =VLOOKUP(F9,Rates!$D$4:$E$8,2) -> 0.1 | J9: =ROUND(E9*I9,2) -> 3088.24 | K9: =PV(H9/12,F9/30,0,-E9) -> 30540.657 | L9: =ROUND(E9-K9,2) -> 341.73 | M9: =F9/E9 -> 0.001133332
A10: RB-100008 | B10: Northgate Trading | C10: Northgate | D10: Business | E10: 6056.98 | F10: 202 | G10: =IF(F10<=30,"Current",IF(F10<=60,"31 to 60 days",IF(F10<=90,"61 to 90 days",IF(F10<=120,"91 to 120 days","Over 120 days")))) -> Over 120 days | H10: =VLOOKUP(D10,Rates!$A$4:$B$7,2,FALSE()) -> 0.115 | I10: =VLOOKUP(F10,Rates!$D$4:$E$8,2) -> 0.85 | J10: =ROUND(E10*I10,2) -> 5148.43 | K10: =PV(H10/12,F10/30,0,-E10) -> 5680.2246 | L10: =ROUND(E10-K10,2) -> 376.76 | M10: =F10/E10 -> 0.033349953
A11: RB-100009 | B11: Kingsford Depot | C11: Kingsford | D11: Internal | E11: 32749.53 | F11: 179 | G11: =IF(F11<=30,"Current",IF(F11<=60,"31 to 60 days",IF(F11<=90,"61 to 90 days",IF(F11<=120,"91 to 120 days","Over 120 days")))) -> Over 120 days | H11: =VLOOKUP(D11,Rates!$A$4:$B$7,2,FALSE()) -> 0.05 | I11: =VLOOKUP(F11,Rates!$D$4:$E$8,2) -> 0.85 | J11: =ROUND(E11*I11,2) -> 27837.1 | K11: =PV(H11/12,F11/30,0,-E11) -> 31947.028 | L11: =ROUND(E11-K11,2) -> 802.5 | M11: =F11/E11 -> 0.0054657273
A12: RB-100010 | B12: Ironwood Outlet 147 | C12: Ironwood | D12: Retail | E12: 16257.77 | F12: 89 | G12: =IF(F12<=30,"Current",IF(F12<=60,"31 to 60 days",IF(F12<=90,"61 to 90 days",IF(F12<=120,"91 to 120 days","Over 120 days")))) -> 61 to 90 days | H12: =VLOOKUP(D12,Rates!$A$4:$B$7,2,FALSE()) -> 0.085 | I12: =VLOOKUP(F12,Rates!$D$4:$E$8,2) -> 0.25 | J12: =ROUND(E12*I12,2) -> 4064.44 | K12: =PV(H12/12,F12/30,0,-E12) -> 15920.875 | L12: =ROUND(E12-K12,2) -> 336.9 | M12: =F12/E12 -> 0.0054743055
A13: RB-100011 | B13: Stonebridge Farms | C13: Stonebridge | D13: Business | E13: 10195.32 | F13: 314 | G13: =IF(F13<=30,"Current",IF(F13<=60,"31 to 60 days",IF(F13<=90,"61 to 90 days",IF(F13<=120,"91 to 120 days","Over 120 days")))) -> Over 120 days | H13: =VLOOKUP(D13,Rates!$A$4:$B$7,2,FALSE()) -> 0.115 | I13: =VLOOKUP(F13,Rates!$D$4:$E$8,2) -> 0.85 | J13: =ROUND(E13*I13,2) -> 8666.02 | K13: =PV(H13/12,F13/30,0,-E13) -> 9226.6941 | L13: =ROUND(E13-K13,2) -> 968.63 | M13: =F13/E13 -> 0.030798445
A14: RB-100012 | B14: Ironwood Outlet 284 | C14: Ironwood | D14: Retail | E14: 33817.61 | F14: 18 | G14: =IF(F14<=30,"Current",IF(F14<=60,"31 to 60 days",IF(F14<=90,"61 to 90 days",IF(F14<=120,"91 to 120 days","Over 120 days")))) -> Current | H14: =VLOOKUP(D14,Rates!$A$4:$B$7,2,FALSE()) -> 0.085 | I14: =VLOOKUP(F14,Rates!$D$4:$E$8,2) -> 0.02 | J14: =ROUND(E14*I14,2) -> 676.35 | K14: =PV(H14/12,F14/30,0,-E14) -> 33674.695 | L14: =ROUND(E14-K14,2) -> 142.92 | M14: =F14/E14 -> 0.00053226706
A15: RB-100013 | B15: Northgate Outlet 301 | C15: Northgate | D15: Wholesale | E15: 14915.07 | F15: 333 | G15: =IF(F15<=30,"Current",IF(F15<=60,"31 to 60 days",IF(F15<=90,"61 to 90 days",IF(F15<=120,"91 to 120 days","Over 120 days")))) -> Over 120 days | H15: =VLOOKUP(D15,Rates!$A$4:$B$7,2,FALSE()) -> 0.02 | I15: =VLOOKUP(F15,Rates!$D$4:$E$8,2) -> 0.85 | J15: =ROUND(E15*I15,2) -> 12677.81 | K15: =PV(H15/12,F15/30,0,-E15) -> 14641.903 | L15: =ROUND(E15-K15,2) -> 273.17 | M15: =F15/E15 -> 0.022326412
A16: RB-100014 | B16: Stonebridge Depot | C16: Stonebridge | D16: Internal | E16: 19285.32 | F16: 287 | G16: =IF(F16<=30,"Current",IF(F16<=60,"31 to 60 days",IF(F16<=90,"61 to 90 days",IF(F16<=120,"91 to 120 days","Over 120 days")))) -> Over 120 days | H16: =VLOOKUP(D16,Rates!$A$4:$B$7,2,FALSE()) -> 0.05 | I16: =VLOOKUP(F16,Rates!$D$4:$E$8,2) -> 0.85 | J16: =ROUND(E16*I16,2) -> 16392.52 | K16: =PV(H16/12,F16/30,0,-E16) -> 18533.24 | L16: =ROUND(E16-K16,2) -> 752.08 | M16: =F16/E16 -> 0.014881786
A17: RB-100015 | B17: Eastwick Butchery | C17: Eastwick | D17: Business | E17: 3378.05 | F17: 9 | G17: =IF(F17<=30,"Current",IF(F17<=60,"31 to 60 days",IF(F17<=90,"61 to 90 days",IF(F17<=120,"91 to 120 days","Over 120 days")))) -> Current | H17: =VLOOKUP(D17,Rates!$A$4:$B$7,2,FALSE()) -> 0.115 | I17: =VLOOKUP(F17,Rates!$D$4:$E$8,2) -> 0.02 | J17: =ROUND(E17*I17,2) -> 67.56 | K17: =PV(H17/12,F17/30,0,-E17) -> 3368.3982 | L17: =ROUND(E17-K17,2) -> 9.65 | M17: =F17/E17 -> 0.002664259
A18: RB-100016 | B18: Kingsford Bakery | C18: Kingsford | D18: Business | E18: 24543.51 | F18: 341 | G18: =IF(F18<=30,"Current",IF(F18<=60,"31 to 60 days",IF(F18<=90,"61 to 90 days",IF(F18<=120,"91 to 120 days","Over 120 days")))) -> Over 120 days | H18: =VLOOKUP(D18,Rates!$A$4:$B$7,2,FALSE()) -> 0.115 | I18: =VLOOKUP(F18,Rates!$D$4:$E$8,2) -> 0.85 | J18: =ROUND(E18*I18,2) -> 20861.98 | K18: =PV(H18/12,F18/30,0,-E18) -> 22021.859 | L18: =ROUND(E18-K18,2) -> 2521.65 | M18: =F18/E18 -> 0.013893693
A19: RB-100017 | B19: Ironwood Outlet 294 | C19: Ironwood | D19: Retail | E19: 40680.69 | F19: 129 | G19: =IF(F19<=30,"Current",IF(F19<=60,"31 to 60 days",IF(F19<=90,"61 to 90 days",IF(F19<=120,"91 to 120 days","Over 120 days")))) -> Over 120 days | H19: =VLOOKUP(D19,Rates!$A$4:$B$7,2,FALSE()) -> 0.085 | I19: =VLOOKUP(F19,Rates!$D$4:$E$8,2) -> 0.85 | J19: =ROUND(E19*I19,2) -> 34578.59 | K19: =PV(H19/12,F19/30,0,-E19) -> 39464.541 | L19: =ROUND(E19-K19,2) -> 1216.15 | M19: =F19/E19 -> 0.0031710377
... A2001: RB-101999 | B2001: Kingsford Depot | C2001: Kingsford | D2001: Internal | E2001: 29145.28 | F2001: 118 | G2001: =IF(F2001<=30,"Current",IF(F2001<=60,"31 to 60 days",IF(F2001<=90,"61 to 90 days",IF(F2001<=120,"91 to 120 days","Over 120 days")))) -> 91 to 120 days | H2001: =VLOOKUP(D2001,Rates!$A$4:$B$7,2,FALSE()) -> 0.05 | I2001: =VLOOKUP(F2001,Rates!$D$4:$E$8,2) -> 0.5 | J2001: =ROUND(E2001*I2001,2) -> 14572.64 | K2001: =PV(H2001/12,F2001/30,0,-E2001) -> 28672.49 | L2001: =ROUND(E2001-K2001,2) -> 472.79 | M2001: =F2001/E2001 -> 0.004048683

Sheet Rates
A1: Riverbend Supply Co. — impairment rates and bands
A3: Debt Type | B3: Discount Rate | D3: Days Overdue From | E3: Provision Percent
A4: Retail | B4: 0.085 | D4: 0 | E4: 0.02
A5: Business | B5: 0.115 | D5: 31 | E5: 0.1
A6: Wholesale | B6: 0.02 | D6: 61 | E6: 0.25
A7: Internal | B7: 0.05 | D7: 91 | E7: 0.5
D8: 121 | E8: 0.85
A11: Tax Rate | B11: 0.15

Sheet Jan
A1: Debt Type | B1: Billed
A2: Retail | B2: 92516.66
A3: Business | B3: 15204.73
A4: Wholesale | B4: 91825.38
A5: Internal | B5: 23760.7

Sheet Feb
A1: Debt Type | B1: Billed
A2: Retail | B2: 27791.82
A3: Business | B3: 32640.34
A4: Wholesale | B4: 49283.14
A5: Internal | B5: 97612.92

Sheet Mar
A1: Debt Type | B1: Billed
A2: Retail | B2: 41966.35
A3: Business | B3: 86571.3
A4: Wholesale | B4: 39685.16
A5: Internal | B5: 95561.74

Sheet Summary
A1: Riverbend Supply Co. — debtor impairment summary
A3: Measure | B3: Value
A4: Total balance | B4: =SUM(Debtors!$E$2:$E$2001) -> 43386901
A5: Total provision | B5: =SUM(Debtors!$J$2:$J$2001) -> 29212863
A6: Total impairment | B6: =SUM(Debtors!$L$2:$L$2001) -> 1597853.9
A7: Average balance | B7: =AVERAGE(Debtors!$E$2:$E$2001) -> 21693.45
A8: Largest balance | B8: =MAX(Debtors!$E$2:$E$2001) -> 45033.43
A9: Accounts | B9: =COUNT(Debtors!$E$2:$E$2001) -> 2000
A10: Business discount rate | B10: =INDEX(Rates!$B$4:$B$7,MATCH("Business",Rates!$A$4:$A$7,0)) -> 0.115
A11: Provision after tax | B11: =ROUND(B5*Tax_Rate,2) -> 4381929.5
A12: Billed, January to March | B12: =SUM(Jan:Mar!B2) -> 162274.83
A13: Billed less provision | B13: =B12-B5 -> -29050589
A14: Balance-weighted rate | B14: =SUMPRODUCT(Debtors!$E$2:$E$2001,Debtors!$H$2:$H$2001)/B4 -> 0.067638968

Sheet Notes
A1: Notes to the impairment calculation
A3: Provision for debtors with balances outstanding over 120 days is raised at 85 percent.
A4: Wholesale accounts are discounted at the reduced rate approved by the board.
A5: The discount rate is applied monthly over the period the account has been overdue.
A6: The rates and bands table is reviewed at each financial year end.
A7: Accounts with a zero balance are retained for audit and excluded from the ratio columns.
